[
  {
      "model": "simplefitapi.description",
      "pk": 1,
      "fields": {
          "description": "Strength Training",
          "user_id": 1
      }
  },
  {
      "model": "simplefitapi.description",
      "pk": 2,
      "fields": {
        "description": "Upper Body",
        "user_id": 1
      }
  },
  {
      "model": "simplefitapi.description",
      "pk": 3,
      "fields": {
        "description": "Lower Body",
        "user_id": 2
      }
  },
  {
    "model": "simplefitapi.description",
    "pk": 4,
    "fields": {
      "description": "Rehabilitation",
      "user_id": 2
    }
  },
  {
    "model": "simplefitapi.description",
    "pk": 5,
    "fields": {
      "description": "Effective",
      "user_id": 1
    }
  }
]
